color_match_tools-3.6.2.dist-info/licenses/LICENSE
color_tools/__init__.py
color_tools/__main__.py
color_tools/cli.py
color_tools/color_deficiency.py
color_tools/config.py
color_tools/constants.py
color_tools/conversions.py
color_tools/distance.py
color_tools/gamut.py
color_tools/matrices.py
color_tools/naming.py
color_tools/palette.py
color_tools/validation.py
color_tools/data/colors.json
color_tools/data/filaments.json
color_tools/data/maker_synonyms.json
color_tools/data/user-colors.json
color_tools/data/user-filaments.json
color_tools/data/user-synonyms.json
color_tools/data/palettes/cga16.json
color_tools/data/palettes/cga4.json
color_tools/data/palettes/commodore64.json
color_tools/data/palettes/ega16.json
color_tools/data/palettes/ega64.json
color_tools/data/palettes/gameboy.json
color_tools/data/palettes/gameboy_dmg.json
color_tools/data/palettes/gameboy_gbl.json
color_tools/data/palettes/gameboy_mgb.json
color_tools/data/palettes/nes.json
color_tools/data/palettes/sms.json
color_tools/data/palettes/vga.json
color_tools/data/palettes/virtualboy.json
color_tools/data/palettes/web.json
color_tools/image/__init__.py
color_tools/image/analysis.py
color_tools/image/basic.py
color_match_tools-3.6.2.dist-info/METADATA
color_match_tools-3.6.2.dist-info/WHEEL
color_match_tools-3.6.2.dist-info/entry_points.txt
color_match_tools-3.6.2.dist-info/top_level.txt
color_match_tools-3.6.2.dist-info/RECORD
