Metadata-Version: 2.4
Name: color-match-tools
Version: 3.6.2
Summary: Comprehensive color science library for accurate color space conversions, perceptual color distance metrics (Delta E), and color matching with CSS and 3D printing filament databases
Author-email: David Terracino <dterracino@gmail.com>
License-Expression: MIT
Project-URL: Homepage, https://github.com/dterracino/color_tools
Project-URL: Repository, https://github.com/dterracino/color_tools
Project-URL: Issues, https://github.com/dterracino/color_tools/issues
Project-URL: Changelog, https://github.com/dterracino/color_tools/blob/main/CHANGELOG.md
Project-URL: Documentation, https://github.com/dterracino/color_tools/blob/main/README.md
Keywords: color,color-science,delta-e,color-conversion,color-matching,rgb,lab,lch,hsl,xyz,ciede2000,cie94,cie76,gamut,srgb,3d-printing,filament
Classifier: Development Status :: 4 - Beta
Classifier: Intended Audience :: Developers
Classifier: Intended Audience :: Science/Research
Classifier: Topic :: Multimedia :: Graphics
Classifier: Topic :: Scientific/Engineering
Classifier: Topic :: Software Development :: Libraries :: Python Modules
Classifier: Programming Language :: Python :: 3
Classifier: Programming Language :: Python :: 3.10
Classifier: Programming Language :: Python :: 3.11
Classifier: Programming Language :: Python :: 3.12
Classifier: Operating System :: OS Independent
Requires-Python: >=3.10
License-File: LICENSE
Provides-Extra: fuzzy
Requires-Dist: fuzzywuzzy>=0.18.0; extra == "fuzzy"
Requires-Dist: python-Levenshtein>=0.12.0; extra == "fuzzy"
Provides-Extra: image
Requires-Dist: Pillow>=10.0.0; extra == "image"
Requires-Dist: numpy>=1.24.0; extra == "image"
Requires-Dist: scikit-image>=0.20.0; extra == "image"
Provides-Extra: docs
Requires-Dist: sphinx>=7.0.0; extra == "docs"
Requires-Dist: sphinx-rtd-theme>=1.3.0; extra == "docs"
Requires-Dist: myst-parser>=2.0.0; extra == "docs"
Requires-Dist: sphinx-autodoc-typehints>=1.24.0; extra == "docs"
Provides-Extra: dev
Requires-Dist: pyright>=1.1.0; extra == "dev"
Requires-Dist: build>=1.0.0; extra == "dev"
Requires-Dist: twine>=4.0.0; extra == "dev"
Provides-Extra: all
Requires-Dist: fuzzywuzzy>=0.18.0; extra == "all"
Requires-Dist: python-Levenshtein>=0.12.0; extra == "all"
Requires-Dist: Pillow>=10.0.0; extra == "all"
Requires-Dist: numpy>=1.24.0; extra == "all"
Requires-Dist: scikit-image>=0.20.0; extra == "all"
Requires-Dist: sphinx>=7.0.0; extra == "all"
Requires-Dist: sphinx-rtd-theme>=1.3.0; extra == "all"
Requires-Dist: myst-parser>=2.0.0; extra == "all"
Requires-Dist: sphinx-autodoc-typehints>=1.24.0; extra == "all"
Dynamic: license-file
